[{"id":"1","types":["grass","poison"],"bases":318,"color":"green","name":"Bulbasaur"},{"id":"2","types":["grass","poison"],"bases":405,"color":"green","name":"Ivysaur"},{"id":"3","types":["grass","poison"],"bases":525,"color":"green","name":"Venusaur"},{"id":"4","types":["fire"],"bases":309,"color":"red","name":"Charmander"},{"id":"5","types":["fire"],"bases":405,"color":"red","name":"Charmeleon"},{"id":"6","types":["fire","flying"],"bases":534,"color":"red","name":"Charizard"},{"id":"7","types":["water"],"bases":314,"color":"blue","name":"Squirtle"},{"id":"8","types":["water"],"bases":405,"color":"blue","name":"Wartortle"},{"id":"9","types":["water"],"bases":530,"color":"blue","name":"Blastoise"},{"id":"10","types":["bug"],"bases":195,"color":"green","name":"Caterpie"},{"id":"11","types":["bug"],"bases":205,"color":"green","name":"Metapod"},{"id":"12","types":["bug","flying"],"bases":395,"color":"white","name":"Butterfree"},{"id":"13","types":["bug","poison"],"bases":195,"color":"brown","name":"Weedle"},{"id":"14","types":["bug","poison"],"bases":205,"color":"yellow","name":"Kakuna"},{"id":"15","types":["bug","poison"],"bases":395,"color":"yellow","name":"Beedrill"},{"id":"16","types":["normal","flying"],"bases":251,"color":"brown","name":"Pidgey"},{"id":"17","types":["normal","flying"],"bases":349,"color":"brown","name":"Pidgeotto"},{"id":"18","types":["normal","flying"],"bases":479,"color":"brown","name":"Pidgeot"},{"id":"19","types":["normal"],"bases":253,"color":"purple","name":"Rattata"},{"id":"20","types":["normal"],"bases":413,"color":"brown","name":"Raticate"},{"id":"21","types":["normal","flying"],"bases":262,"color":"brown","name":"Spearow"},{"id":"22","types":["normal","flying"],"bases":442,"color":"brown","name":"Fearow"},{"id":"23","types":["poison"],"bases":288,"color":"purple","name":"Ekans"},{"id":"24","types":["poison"],"bases":448,"color":"purple","name":"Arbok"},{"id":"25","types":["electric"],"bases":320,"color":"yellow","name":"Pikachu"},{"id":"26","types":["electric"],"bases":485,"color":"yellow","name":"Raichu"},{"id":"27","types":["ground"],"bases":300,"color":"yellow","name":"Sandshrew"},{"id":"28","types":["ground"],"bases":450,"color":"yellow","name":"Sandslash"},{"id":"29","types":["poison"],"bases":275,"color":"blue","name":"Nidoran♀"},{"id":"30","types":["poison"],"bases":365,"color":"blue","name":"Nidorina"},{"id":"31","types":["poison","ground"],"bases":505,"color":"blue","name":"Nidoqueen"},{"id":"32","types":["poison"],"bases":273,"color":"purple","name":"Nidoran♂"},{"id":"33","types":["poison"],"bases":365,"color":"purple","name":"Nidorino"},{"id":"34","types":["poison","ground"],"bases":505,"color":"purple","name":"Nidoking"},{"id":"35","types":["fairy"],"bases":323,"color":"pink","name":"Clefairy"},{"id":"36","types":["fairy"],"bases":483,"color":"pink","name":"Clefable"},{"id":"37","types":["fire"],"bases":299,"color":"brown","name":"Vulpix"},{"id":"38","types":["fire"],"bases":505,"color":"yellow","name":"Ninetales"},{"id":"39","types":["normal","fairy"],"bases":270,"color":"pink","name":"Jigglypuff"},{"id":"40","types":["normal","fairy"],"bases":435,"color":"pink","name":"Wigglytuff"},{"id":"41","types":["poison","flying"],"bases":245,"color":"purple","name":"Zubat"},{"id":"42","types":["poison","flying"],"bases":455,"color":"purple","name":"Golbat"},{"id":"43","types":["grass","poison"],"bases":320,"color":"blue","name":"Oddish"},{"id":"44","types":["grass","poison"],"bases":395,"color":"blue","name":"Gloom"},{"id":"45","types":["grass","poison"],"bases":490,"color":"red","name":"Vileplume"},{"id":"46","types":["bug","grass"],"bases":285,"color":"red","name":"Paras"},{"id":"47","types":["bug","grass"],"bases":405,"color":"red","name":"Parasect"},{"id":"48","types":["bug","poison"],"bases":305,"color":"purple","name":"Venonat"},{"id":"49","types":["bug","poison"],"bases":450,"color":"purple","name":"Venomoth"},{"id":"50","types":["ground"],"bases":265,"color":"brown","name":"Diglett"},{"id":"51","types":["ground"],"bases":425,"color":"brown","name":"Dugtrio"},{"id":"52","types":["normal"],"bases":290,"color":"yellow","name":"Meowth"},{"id":"53","types":["normal"],"bases":440,"color":"yellow","name":"Persian"},{"id":"54","types":["water"],"bases":320,"color":"yellow","name":"Psyduck"},{"id":"55","types":["water"],"bases":500,"color":"blue","name":"Golduck"},{"id":"56","types":["fighting"],"bases":305,"color":"brown","name":"Mankey"},{"id":"57","types":["fighting"],"bases":455,"color":"brown","name":"Primeape"},{"id":"58","types":["fire"],"bases":350,"color":"brown","name":"Growlithe"},{"id":"59","types":["fire"],"bases":555,"color":"brown","name":"Arcanine"},{"id":"60","types":["water"],"bases":300,"color":"blue","name":"Poliwag"},{"id":"61","types":["water"],"bases":385,"color":"blue","name":"Poliwhirl"},{"id":"62","types":["water","fighting"],"bases":510,"color":"blue","name":"Poliwrath"},{"id":"63","types":["psychic"],"bases":310,"color":"brown","name":"Abra"},{"id":"64","types":["psychic"],"bases":400,"color":"brown","name":"Kadabra"},{"id":"65","types":["psychic"],"bases":500,"color":"brown","name":"Alakazam"},{"id":"66","types":["fighting"],"bases":305,"color":"gray","name":"Machop"},{"id":"67","types":["fighting"],"bases":405,"color":"gray","name":"Machoke"},{"id":"68","types":["fighting"],"bases":505,"color":"gray","name":"Machamp"},{"id":"69","types":["grass","poison"],"bases":300,"color":"green","name":"Bellsprout"},{"id":"70","types":["grass","poison"],"bases":390,"color":"green","name":"Weepinbell"},{"id":"71","types":["grass","poison"],"bases":490,"color":"green","name":"Victreebel"},{"id":"72","types":["water","poison"],"bases":335,"color":"blue","name":"Tentacool"},{"id":"73","types":["water","poison"],"bases":515,"color":"blue","name":"Tentacruel"},{"id":"74","types":["rock","ground"],"bases":300,"color":"brown","name":"Geodude"},{"id":"75","types":["rock","ground"],"bases":390,"color":"brown","name":"Graveler"},{"id":"76","types":["rock","ground"],"bases":495,"color":"brown","name":"Golem"},{"id":"77","types":["fire"],"bases":410,"color":"yellow","name":"Ponyta"},{"id":"78","types":["fire"],"bases":500,"color":"yellow","name":"Rapidash"},{"id":"79","types":["water","psychic"],"bases":315,"color":"pink","name":"Slowpoke"},{"id":"80","types":["water","psychic"],"bases":490,"color":"pink","name":"Slowbro"},{"id":"81","types":["electric","steel"],"bases":325,"color":"gray","name":"Magnemite"},{"id":"82","types":["electric","steel"],"bases":465,"color":"gray","name":"Magneton"},{"id":"83","types":["normal","flying"],"bases":377,"color":"brown","name":"Farfetch’d"},{"id":"84","types":["normal","flying"],"bases":310,"color":"brown","name":"Doduo"},{"id":"85","types":["normal","flying"],"bases":470,"color":"brown","name":"Dodrio"},{"id":"86","types":["water"],"bases":325,"color":"white","name":"Seel"},{"id":"87","types":["water","ice"],"bases":475,"color":"white","name":"Dewgong"},{"id":"88","types":["poison"],"bases":325,"color":"purple","name":"Grimer"},{"id":"89","types":["poison"],"bases":500,"color":"purple","name":"Muk"},{"id":"90","types":["water"],"bases":305,"color":"purple","name":"Shellder"},{"id":"91","types":["water","ice"],"bases":525,"color":"purple","name":"Cloyster"},{"id":"92","types":["ghost","poison"],"bases":310,"color":"purple","name":"Gastly"},{"id":"93","types":["ghost","poison"],"bases":405,"color":"purple","name":"Haunter"},{"id":"94","types":["ghost","poison"],"bases":500,"color":"purple","name":"Gengar"},{"id":"95","types":["rock","ground"],"bases":385,"color":"gray","name":"Onix"},{"id":"96","types":["psychic"],"bases":328,"color":"yellow","name":"Drowzee"},{"id":"97","types":["psychic"],"bases":483,"color":"yellow","name":"Hypno"},{"id":"98","types":["water"],"bases":325,"color":"red","name":"Krabby"},{"id":"99","types":["water"],"bases":475,"color":"red","name":"Kingler"},{"id":"100","types":["electric"],"bases":330,"color":"red","name":"Voltorb"},{"id":"101","types":["electric"],"bases":490,"color":"red","name":"Electrode"},{"id":"102","types":["grass","psychic"],"bases":325,"color":"pink","name":"Exeggcute"},{"id":"103","types":["grass","psychic"],"bases":530,"color":"yellow","name":"Exeggutor"},{"id":"104","types":["ground"],"bases":320,"color":"brown","name":"Cubone"},{"id":"105","types":["ground"],"bases":425,"color":"brown","name":"Marowak"},{"id":"106","types":["fighting"],"bases":455,"color":"brown","name":"Hitmonlee"},{"id":"107","types":["fighting"],"bases":455,"color":"brown","name":"Hitmonchan"},{"id":"108","types":["normal"],"bases":385,"color":"pink","name":"Lickitung"},{"id":"109","types":["poison"],"bases":340,"color":"purple","name":"Koffing"},{"id":"110","types":["poison"],"bases":490,"color":"purple","name":"Weezing"},{"id":"111","types":["ground","rock"],"bases":345,"color":"gray","name":"Rhyhorn"},{"id":"112","types":["ground","rock"],"bases":485,"color":"gray","name":"Rhydon"},{"id":"113","types":["normal"],"bases":450,"color":"pink","name":"Chansey"},{"id":"114","types":["grass"],"bases":435,"color":"blue","name":"Tangela"},{"id":"115","types":["normal"],"bases":490,"color":"brown","name":"Kangaskhan"},{"id":"116","types":["water"],"bases":295,"color":"blue","name":"Horsea"},{"id":"117","types":["water"],"bases":440,"color":"blue","name":"Seadra"},{"id":"118","types":["water"],"bases":320,"color":"red","name":"Goldeen"},{"id":"119","types":["water"],"bases":450,"color":"red","name":"Seaking"},{"id":"120","types":["water"],"bases":340,"color":"brown","name":"Staryu"},{"id":"121","types":["water","psychic"],"bases":520,"color":"purple","name":"Starmie"},{"id":"122","types":["psychic","fairy"],"bases":460,"color":"pink","name":"Mr. Mime"},{"id":"123","types":["bug","flying"],"bases":500,"color":"green","name":"Scyther"},{"id":"124","types":["ice","psychic"],"bases":455,"color":"red","name":"Jynx"},{"id":"125","types":["electric"],"bases":490,"color":"yellow","name":"Electabuzz"},{"id":"126","types":["fire"],"bases":495,"color":"red","name":"Magmar"},{"id":"127","types":["bug"],"bases":500,"color":"brown","name":"Pinsir"},{"id":"128","types":["normal"],"bases":490,"color":"brown","name":"Tauros"},{"id":"129","types":["water"],"bases":200,"color":"red","name":"Magikarp"},{"id":"130","types":["water","flying"],"bases":540,"color":"blue","name":"Gyarados"},{"id":"131","types":["water","ice"],"bases":535,"color":"blue","name":"Lapras"},{"id":"132","types":["normal"],"bases":288,"color":"purple","name":"Ditto"},{"id":"133","types":["normal"],"bases":325,"color":"brown","name":"Eevee"},{"id":"134","types":["water"],"bases":525,"color":"blue","name":"Vaporeon"},{"id":"135","types":["electric"],"bases":525,"color":"yellow","name":"Jolteon"},{"id":"136","types":["fire"],"bases":525,"color":"red","name":"Flareon"},{"id":"137","types":["normal"],"bases":395,"color":"pink","name":"Porygon"},{"id":"138","types":["rock","water"],"bases":355,"color":"blue","name":"Omanyte"},{"id":"139","types":["rock","water"],"bases":495,"color":"blue","name":"Omastar"},{"id":"140","types":["rock","water"],"bases":355,"color":"brown","name":"Kabuto"},{"id":"141","types":["rock","water"],"bases":495,"color":"brown","name":"Kabutops"},{"id":"142","types":["rock","flying"],"bases":515,"color":"purple","name":"Aerodactyl"},{"id":"143","types":["normal"],"bases":540,"color":"black","name":"Snorlax"},{"id":"144","types":["ice","flying"],"bases":580,"color":"blue","name":"Articuno"},{"id":"145","types":["electric","flying"],"bases":580,"color":"yellow","name":"Zapdos"},{"id":"146","types":["fire","flying"],"bases":580,"color":"yellow","name":"Moltres"},{"id":"147","types":["dragon"],"bases":300,"color":"blue","name":"Dratini"},{"id":"148","types":["dragon"],"bases":420,"color":"blue","name":"Dragonair"},{"id":"149","types":["dragon","flying"],"bases":600,"color":"brown","name":"Dragonite"},{"id":"150","types":["psychic"],"bases":680,"color":"purple","name":"Mewtwo"},{"id":"151","types":["psychic"],"bases":600,"color":"pink","name":"Mew"},{"id":"152","types":["grass"],"bases":318,"color":"green","name":"Chikorita"},{"id":"153","types":["grass"],"bases":405,"color":"green","name":"Bayleef"},{"id":"154","types":["grass"],"bases":525,"color":"green","name":"Meganium"},{"id":"155","types":["fire"],"bases":309,"color":"yellow","name":"Cyndaquil"},{"id":"156","types":["fire"],"bases":405,"color":"yellow","name":"Quilava"},{"id":"157","types":["fire"],"bases":534,"color":"yellow","name":"Typhlosion"},{"id":"158","types":["water"],"bases":314,"color":"blue","name":"Totodile"},{"id":"159","types":["water"],"bases":405,"color":"blue","name":"Croconaw"},{"id":"160","types":["water"],"bases":530,"color":"blue","name":"Feraligatr"},{"id":"161","types":["normal"],"bases":215,"color":"brown","name":"Sentret"},{"id":"162","types":["normal"],"bases":415,"color":"brown","name":"Furret"},{"id":"163","types":["normal","flying"],"bases":262,"color":"brown","name":"Hoothoot"},{"id":"164","types":["normal","flying"],"bases":452,"color":"brown","name":"Noctowl"},{"id":"165","types":["bug","flying"],"bases":265,"color":"red","name":"Ledyba"},{"id":"166","types":["bug","flying"],"bases":390,"color":"red","name":"Ledian"},{"id":"167","types":["bug","poison"],"bases":250,"color":"green","name":"Spinarak"},{"id":"168","types":["bug","poison"],"bases":400,"color":"red","name":"Ariados"},{"id":"169","types":["poison","flying"],"bases":535,"color":"purple","name":"Crobat"},{"id":"170","types":["water","electric"],"bases":330,"color":"blue","name":"Chinchou"},{"id":"171","types":["water","electric"],"bases":460,"color":"blue","name":"Lanturn"},{"id":"172","types":["electric"],"bases":205,"color":"yellow","name":"Pichu"},{"id":"173","types":["fairy"],"bases":218,"color":"pink","name":"Cleffa"},{"id":"174","types":["normal","fairy"],"bases":210,"color":"pink","name":"Igglybuff"},{"id":"175","types":["fairy"],"bases":245,"color":"white","name":"Togepi"},{"id":"176","types":["fairy","flying"],"bases":405,"color":"white","name":"Togetic"},{"id":"177","types":["psychic","flying"],"bases":320,"color":"green","name":"Natu"},{"id":"178","types":["psychic","flying"],"bases":470,"color":"green","name":"Xatu"},{"id":"179","types":["electric"],"bases":280,"color":"white","name":"Mareep"},{"id":"180","types":["electric"],"bases":365,"color":"pink","name":"Flaaffy"},{"id":"181","types":["electric"],"bases":510,"color":"yellow","name":"Ampharos"},{"id":"182","types":["grass"],"bases":490,"color":"green","name":"Bellossom"},{"id":"183","types":["water","fairy"],"bases":250,"color":"blue","name":"Marill"},{"id":"184","types":["water","fairy"],"bases":420,"color":"blue","name":"Azumarill"},{"id":"185","types":["rock"],"bases":410,"color":"brown","name":"Sudowoodo"},{"id":"186","types":["water"],"bases":500,"color":"green","name":"Politoed"},{"id":"187","types":["grass","flying"],"bases":250,"color":"pink","name":"Hoppip"},{"id":"188","types":["grass","flying"],"bases":340,"color":"green","name":"Skiploom"},{"id":"189","types":["grass","flying"],"bases":460,"color":"blue","name":"Jumpluff"},{"id":"190","types":["normal"],"bases":360,"color":"purple","name":"Aipom"},{"id":"191","types":["grass"],"bases":180,"color":"yellow","name":"Sunkern"},{"id":"192","types":["grass"],"bases":425,"color":"yellow","name":"Sunflora"},{"id":"193","types":["bug","flying"],"bases":390,"color":"red","name":"Yanma"},{"id":"194","types":["water","ground"],"bases":210,"color":"blue","name":"Wooper"},{"id":"195","types":["water","ground"],"bases":430,"color":"blue","name":"Quagsire"},{"id":"196","types":["psychic"],"bases":525,"color":"purple","name":"Espeon"},{"id":"197","types":["dark"],"bases":525,"color":"black","name":"Umbreon"},{"id":"198","types":["dark","flying"],"bases":405,"color":"black","name":"Murkrow"},{"id":"199","types":["water","psychic"],"bases":490,"color":"pink","name":"Slowking"},{"id":"200","types":["ghost"],"bases":435,"color":"gray","name":"Misdreavus"},{"id":"201","types":["psychic"],"bases":336,"color":"black","name":"Unown"},{"id":"202","types":["psychic"],"bases":405,"color":"blue","name":"Wobbuffet"},{"id":"203","types":["normal","psychic"],"bases":455,"color":"yellow","name":"Girafarig"},{"id":"204","types":["bug"],"bases":290,"color":"gray","name":"Pineco"},{"id":"205","types":["bug","steel"],"bases":465,"color":"purple","name":"Forretress"},{"id":"206","types":["normal"],"bases":415,"color":"yellow","name":"Dunsparce"},{"id":"207","types":["ground","flying"],"bases":430,"color":"purple","name":"Gligar"},{"id":"208","types":["steel","ground"],"bases":510,"color":"gray","name":"Steelix"},{"id":"209","types":["fairy"],"bases":300,"color":"pink","name":"Snubbull"},{"id":"210","types":["fairy"],"bases":450,"color":"purple","name":"Granbull"},{"id":"211","types":["water","poison"],"bases":440,"color":"gray","name":"Qwilfish"},{"id":"212","types":["bug","steel"],"bases":500,"color":"red","name":"Scizor"},{"id":"213","types":["bug","rock"],"bases":505,"color":"yellow","name":"Shuckle"},{"id":"214","types":["bug","fighting"],"bases":500,"color":"blue","name":"Heracross"},{"id":"215","types":["dark","ice"],"bases":430,"color":"black","name":"Sneasel"},{"id":"216","types":["normal"],"bases":330,"color":"brown","name":"Teddiursa"},{"id":"217","types":["normal"],"bases":500,"color":"brown","name":"Ursaring"},{"id":"218","types":["fire"],"bases":250,"color":"red","name":"Slugma"},{"id":"219","types":["fire","rock"],"bases":430,"color":"red","name":"Magcargo"},{"id":"220","types":["ice","ground"],"bases":250,"color":"brown","name":"Swinub"},{"id":"221","types":["ice","ground"],"bases":450,"color":"brown","name":"Piloswine"},{"id":"222","types":["water","rock"],"bases":410,"color":"pink","name":"Corsola"},{"id":"223","types":["water"],"bases":300,"color":"gray","name":"Remoraid"},{"id":"224","types":["water"],"bases":480,"color":"red","name":"Octillery"},{"id":"225","types":["ice","flying"],"bases":330,"color":"red","name":"Delibird"},{"id":"226","types":["water","flying"],"bases":485,"color":"purple","name":"Mantine"},{"id":"227","types":["steel","flying"],"bases":465,"color":"gray","name":"Skarmory"},{"id":"228","types":["dark","fire"],"bases":330,"color":"black","name":"Houndour"},{"id":"229","types":["dark","fire"],"bases":500,"color":"black","name":"Houndoom"},{"id":"230","types":["water","dragon"],"bases":540,"color":"blue","name":"Kingdra"},{"id":"231","types":["ground"],"bases":330,"color":"blue","name":"Phanpy"},{"id":"232","types":["ground"],"bases":500,"color":"gray","name":"Donphan"},{"id":"233","types":["normal"],"bases":515,"color":"red","name":"Porygon2"},{"id":"234","types":["normal"],"bases":465,"color":"brown","name":"Stantler"},{"id":"235","types":["normal"],"bases":250,"color":"white","name":"Smeargle"},{"id":"236","types":["fighting"],"bases":210,"color":"purple","name":"Tyrogue"},{"id":"237","types":["fighting"],"bases":455,"color":"brown","name":"Hitmontop"},{"id":"238","types":["ice","psychic"],"bases":305,"color":"pink","name":"Smoochum"},{"id":"239","types":["electric"],"bases":360,"color":"yellow","name":"Elekid"},{"id":"240","types":["fire"],"bases":365,"color":"red","name":"Magby"},{"id":"241","types":["normal"],"bases":490,"color":"pink","name":"Miltank"},{"id":"242","types":["normal"],"bases":540,"color":"pink","name":"Blissey"},{"id":"243","types":["electric"],"bases":580,"color":"yellow","name":"Raikou"},{"id":"244","types":["fire"],"bases":580,"color":"brown","name":"Entei"},{"id":"245","types":["water"],"bases":580,"color":"blue","name":"Suicune"},{"id":"246","types":["rock","ground"],"bases":300,"color":"green","name":"Larvitar"},{"id":"247","types":["rock","ground"],"bases":410,"color":"gray","name":"Pupitar"},{"id":"248","types":["rock","dark"],"bases":600,"color":"green","name":"Tyranitar"},{"id":"249","types":["psychic","flying"],"bases":680,"color":"white","name":"Lugia"},{"id":"250","types":["fire","flying"],"bases":680,"color":"red","name":"Ho-Oh"},{"id":"251","types":["psychic","grass"],"bases":600,"color":"green","name":"Celebi"},{"id":"252","types":["grass"],"bases":310,"color":"green","name":"Treecko"},{"id":"253","types":["grass"],"bases":405,"color":"green","name":"Grovyle"},{"id":"254","types":["grass"],"bases":530,"color":"green","name":"Sceptile"},{"id":"255","types":["fire"],"bases":310,"color":"red","name":"Torchic"},{"id":"256","types":["fire","fighting"],"bases":405,"color":"red","name":"Combusken"},{"id":"257","types":["fire","fighting"],"bases":530,"color":"red","name":"Blaziken"},{"id":"258","types":["water"],"bases":310,"color":"blue","name":"Mudkip"},{"id":"259","types":["water","ground"],"bases":405,"color":"blue","name":"Marshtomp"},{"id":"260","types":["water","ground"],"bases":535,"color":"blue","name":"Swampert"},{"id":"261","types":["dark"],"bases":220,"color":"gray","name":"Poochyena"},{"id":"262","types":["dark"],"bases":420,"color":"gray","name":"Mightyena"},{"id":"263","types":["normal"],"bases":240,"color":"brown","name":"Zigzagoon"},{"id":"264","types":["normal"],"bases":420,"color":"white","name":"Linoone"},{"id":"265","types":["bug"],"bases":195,"color":"red","name":"Wurmple"},{"id":"266","types":["bug"],"bases":205,"color":"white","name":"Silcoon"},{"id":"267","types":["bug","flying"],"bases":395,"color":"yellow","name":"Beautifly"},{"id":"268","types":["bug"],"bases":205,"color":"purple","name":"Cascoon"},{"id":"269","types":["bug","poison"],"bases":385,"color":"green","name":"Dustox"},{"id":"270","types":["water","grass"],"bases":220,"color":"green","name":"Lotad"},{"id":"271","types":["water","grass"],"bases":340,"color":"green","name":"Lombre"},{"id":"272","types":["water","grass"],"bases":480,"color":"green","name":"Ludicolo"},{"id":"273","types":["grass"],"bases":220,"color":"brown","name":"Seedot"},{"id":"274","types":["grass","dark"],"bases":340,"color":"brown","name":"Nuzleaf"},{"id":"275","types":["grass","dark"],"bases":480,"color":"brown","name":"Shiftry"},{"id":"276","types":["normal","flying"],"bases":270,"color":"blue","name":"Taillow"},{"id":"277","types":["normal","flying"],"bases":455,"color":"blue","name":"Swellow"},{"id":"278","types":["water","flying"],"bases":270,"color":"white","name":"Wingull"},{"id":"279","types":["water","flying"],"bases":440,"color":"yellow","name":"Pelipper"},{"id":"280","types":["psychic","fairy"],"bases":198,"color":"white","name":"Ralts"},{"id":"281","types":["psychic","fairy"],"bases":278,"color":"white","name":"Kirlia"},{"id":"282","types":["psychic","fairy"],"bases":518,"color":"white","name":"Gardevoir"},{"id":"283","types":["bug","water"],"bases":269,"color":"blue","name":"Surskit"},{"id":"284","types":["bug","flying"],"bases":454,"color":"blue","name":"Masquerain"},{"id":"285","types":["grass"],"bases":295,"color":"brown","name":"Shroomish"},{"id":"286","types":["grass","fighting"],"bases":460,"color":"green","name":"Breloom"},{"id":"287","types":["normal"],"bases":280,"color":"brown","name":"Slakoth"},{"id":"288","types":["normal"],"bases":440,"color":"white","name":"Vigoroth"},{"id":"289","types":["normal"],"bases":670,"color":"brown","name":"Slaking"},{"id":"290","types":["bug","ground"],"bases":266,"color":"gray","name":"Nincada"},{"id":"291","types":["bug","flying"],"bases":456,"color":"yellow","name":"Ninjask"},{"id":"292","types":["bug","ghost"],"bases":236,"color":"brown","name":"Shedinja"},{"id":"293","types":["normal"],"bases":240,"color":"pink","name":"Whismur"},{"id":"294","types":["normal"],"bases":360,"color":"blue","name":"Loudred"},{"id":"295","types":["normal"],"bases":490,"color":"blue","name":"Exploud"},{"id":"296","types":["fighting"],"bases":237,"color":"yellow","name":"Makuhita"},{"id":"297","types":["fighting"],"bases":474,"color":"brown","name":"Hariyama"},{"id":"298","types":["normal","fairy"],"bases":190,"color":"blue","name":"Azurill"},{"id":"299","types":["rock"],"bases":375,"color":"gray","name":"Nosepass"},{"id":"300","types":["normal"],"bases":260,"color":"pink","name":"Skitty"},{"id":"301","types":["normal"],"bases":400,"color":"purple","name":"Delcatty"},{"id":"302","types":["dark","ghost"],"bases":380,"color":"purple","name":"Sableye"},{"id":"303","types":["steel","fairy"],"bases":380,"color":"black","name":"Mawile"},{"id":"304","types":["steel","rock"],"bases":330,"color":"gray","name":"Aron"},{"id":"305","types":["steel","rock"],"bases":430,"color":"gray","name":"Lairon"},{"id":"306","types":["steel","rock"],"bases":530,"color":"gray","name":"Aggron"},{"id":"307","types":["fighting","psychic"],"bases":280,"color":"blue","name":"Meditite"},{"id":"308","types":["fighting","psychic"],"bases":410,"color":"red","name":"Medicham"},{"id":"309","types":["electric"],"bases":295,"color":"green","name":"Electrike"},{"id":"310","types":["electric"],"bases":475,"color":"yellow","name":"Manectric"},{"id":"311","types":["electric"],"bases":405,"color":"yellow","name":"Plusle"},{"id":"312","types":["electric"],"bases":405,"color":"yellow","name":"Minun"},{"id":"313","types":["bug"],"bases":430,"color":"gray","name":"Volbeat"},{"id":"314","types":["bug"],"bases":430,"color":"purple","name":"Illumise"},{"id":"315","types":["grass","poison"],"bases":400,"color":"green","name":"Roselia"},{"id":"316","types":["poison"],"bases":302,"color":"green","name":"Gulpin"},{"id":"317","types":["poison"],"bases":467,"color":"purple","name":"Swalot"},{"id":"318","types":["water","dark"],"bases":305,"color":"red","name":"Carvanha"},{"id":"319","types":["water","dark"],"bases":460,"color":"blue","name":"Sharpedo"},{"id":"320","types":["water"],"bases":400,"color":"blue","name":"Wailmer"},{"id":"321","types":["water"],"bases":500,"color":"blue","name":"Wailord"},{"id":"322","types":["fire","ground"],"bases":305,"color":"yellow","name":"Numel"},{"id":"323","types":["fire","ground"],"bases":460,"color":"red","name":"Camerupt"},{"id":"324","types":["fire"],"bases":470,"color":"brown","name":"Torkoal"},{"id":"325","types":["psychic"],"bases":330,"color":"black","name":"Spoink"},{"id":"326","types":["psychic"],"bases":470,"color":"purple","name":"Grumpig"},{"id":"327","types":["normal"],"bases":360,"color":"brown","name":"Spinda"},{"id":"328","types":["ground"],"bases":290,"color":"brown","name":"Trapinch"},{"id":"329","types":["ground","dragon"],"bases":340,"color":"green","name":"Vibrava"},{"id":"330","types":["ground","dragon"],"bases":520,"color":"green","name":"Flygon"},{"id":"331","types":["grass"],"bases":335,"color":"green","name":"Cacnea"},{"id":"332","types":["grass","dark"],"bases":475,"color":"green","name":"Cacturne"},{"id":"333","types":["normal","flying"],"bases":310,"color":"blue","name":"Swablu"},{"id":"334","types":["dragon","flying"],"bases":490,"color":"blue","name":"Altaria"},{"id":"335","types":["normal"],"bases":458,"color":"white","name":"Zangoose"},{"id":"336","types":["poison"],"bases":458,"color":"black","name":"Seviper"},{"id":"337","types":["rock","psychic"],"bases":460,"color":"yellow","name":"Lunatone"},{"id":"338","types":["rock","psychic"],"bases":460,"color":"red","name":"Solrock"},{"id":"339","types":["water","ground"],"bases":288,"color":"gray","name":"Barboach"},{"id":"340","types":["water","ground"],"bases":468,"color":"blue","name":"Whiscash"},{"id":"341","types":["water"],"bases":308,"color":"red","name":"Corphish"},{"id":"342","types":["water","dark"],"bases":468,"color":"red","name":"Crawdaunt"},{"id":"343","types":["ground","psychic"],"bases":300,"color":"brown","name":"Baltoy"},{"id":"344","types":["ground","psychic"],"bases":500,"color":"black","name":"Claydol"},{"id":"345","types":["rock","grass"],"bases":355,"color":"purple","name":"Lileep"},{"id":"346","types":["rock","grass"],"bases":495,"color":"green","name":"Cradily"},{"id":"347","types":["rock","bug"],"bases":355,"color":"gray","name":"Anorith"},{"id":"348","types":["rock","bug"],"bases":495,"color":"gray","name":"Armaldo"},{"id":"349","types":["water"],"bases":200,"color":"brown","name":"Feebas"},{"id":"350","types":["water"],"bases":540,"color":"pink","name":"Milotic"},{"id":"351","types":["normal"],"bases":420,"color":"gray","name":"Castform"},{"id":"352","types":["normal"],"bases":440,"color":"green","name":"Kecleon"},{"id":"353","types":["ghost"],"bases":295,"color":"black","name":"Shuppet"},{"id":"354","types":["ghost"],"bases":455,"color":"black","name":"Banette"},{"id":"355","types":["ghost"],"bases":295,"color":"black","name":"Duskull"},{"id":"356","types":["ghost"],"bases":455,"color":"black","name":"Dusclops"},{"id":"357","types":["grass","flying"],"bases":460,"color":"green","name":"Tropius"},{"id":"358","types":["psychic"],"bases":455,"color":"blue","name":"Chimecho"},{"id":"359","types":["dark"],"bases":465,"color":"white","name":"Absol"},{"id":"360","types":["psychic"],"bases":260,"color":"blue","name":"Wynaut"},{"id":"361","types":["ice"],"bases":300,"color":"gray","name":"Snorunt"},{"id":"362","types":["ice"],"bases":480,"color":"gray","name":"Glalie"},{"id":"363","types":["ice","water"],"bases":290,"color":"blue","name":"Spheal"},{"id":"364","types":["ice","water"],"bases":410,"color":"blue","name":"Sealeo"},{"id":"365","types":["ice","water"],"bases":530,"color":"blue","name":"Walrein"},{"id":"366","types":["water"],"bases":345,"color":"blue","name":"Clamperl"},{"id":"367","types":["water"],"bases":485,"color":"blue","name":"Huntail"},{"id":"368","types":["water"],"bases":485,"color":"pink","name":"Gorebyss"},{"id":"369","types":["water","rock"],"bases":485,"color":"gray","name":"Relicanth"},{"id":"370","types":["water"],"bases":330,"color":"pink","name":"Luvdisc"},{"id":"371","types":["dragon"],"bases":300,"color":"blue","name":"Bagon"},{"id":"372","types":["dragon"],"bases":420,"color":"white","name":"Shelgon"},{"id":"373","types":["dragon","flying"],"bases":600,"color":"blue","name":"Salamence"},{"id":"374","types":["steel","psychic"],"bases":300,"color":"blue","name":"Beldum"},{"id":"375","types":["steel","psychic"],"bases":420,"color":"blue","name":"Metang"},{"id":"376","types":["steel","psychic"],"bases":600,"color":"blue","name":"Metagross"},{"id":"377","types":["rock"],"bases":580,"color":"brown","name":"Regirock"},{"id":"378","types":["ice"],"bases":580,"color":"blue","name":"Regice"},{"id":"379","types":["steel"],"bases":580,"color":"gray","name":"Registeel"},{"id":"380","types":["dragon","psychic"],"bases":600,"color":"red","name":"Latias"},{"id":"381","types":["dragon","psychic"],"bases":600,"color":"blue","name":"Latios"},{"id":"382","types":["water"],"bases":670,"color":"blue","name":"Kyogre"},{"id":"383","types":["ground"],"bases":670,"color":"red","name":"Groudon"},{"id":"384","types":["dragon","flying"],"bases":680,"color":"green","name":"Rayquaza"},{"id":"385","types":["steel","psychic"],"bases":600,"color":"yellow","name":"Jirachi"},{"id":"386","types":["psychic"],"bases":600,"color":"red","name":"Normal Deoxys"},{"id":"387","types":["grass"],"bases":318,"color":"green","name":"Turtwig"},{"id":"388","types":["grass"],"bases":405,"color":"green","name":"Grotle"},{"id":"389","types":["grass","ground"],"bases":525,"color":"green","name":"Torterra"},{"id":"390","types":["fire"],"bases":309,"color":"brown","name":"Chimchar"},{"id":"391","types":["fire","fighting"],"bases":405,"color":"brown","name":"Monferno"},{"id":"392","types":["fire","fighting"],"bases":534,"color":"brown","name":"Infernape"},{"id":"393","types":["water"],"bases":314,"color":"blue","name":"Piplup"},{"id":"394","types":["water"],"bases":405,"color":"blue","name":"Prinplup"},{"id":"395","types":["water","steel"],"bases":530,"color":"blue","name":"Empoleon"},{"id":"396","types":["normal","flying"],"bases":245,"color":"brown","name":"Starly"},{"id":"397","types":["normal","flying"],"bases":340,"color":"brown","name":"Staravia"},{"id":"398","types":["normal","flying"],"bases":485,"color":"brown","name":"Staraptor"},{"id":"399","types":["normal"],"bases":250,"color":"brown","name":"Bidoof"},{"id":"400","types":["normal","water"],"bases":410,"color":"brown","name":"Bibarel"},{"id":"401","types":["bug"],"bases":194,"color":"red","name":"Kricketot"},{"id":"402","types":["bug"],"bases":384,"color":"red","name":"Kricketune"},{"id":"403","types":["electric"],"bases":263,"color":"blue","name":"Shinx"},{"id":"404","types":["electric"],"bases":363,"color":"blue","name":"Luxio"},{"id":"405","types":["electric"],"bases":523,"color":"blue","name":"Luxray"},{"id":"406","types":["grass","poison"],"bases":280,"color":"green","name":"Budew"},{"id":"407","types":["grass","poison"],"bases":515,"color":"green","name":"Roserade"},{"id":"408","types":["rock"],"bases":350,"color":"blue","name":"Cranidos"},{"id":"409","types":["rock"],"bases":495,"color":"blue","name":"Rampardos"},{"id":"410","types":["rock","steel"],"bases":350,"color":"gray","name":"Shieldon"},{"id":"411","types":["rock","steel"],"bases":495,"color":"gray","name":"Bastiodon"},{"id":"412","types":["bug"],"bases":224,"color":"green","name":"Burmy"},{"id":"413","types":["bug","grass"],"bases":424,"color":"green","name":"Plant Wormadam"},{"id":"414","types":["bug","flying"],"bases":424,"color":"yellow","name":"Mothim"},{"id":"415","types":["bug","flying"],"bases":244,"color":"yellow","name":"Combee"},{"id":"416","types":["bug","flying"],"bases":474,"color":"yellow","name":"Vespiquen"},{"id":"417","types":["electric"],"bases":405,"color":"white","name":"Pachirisu"},{"id":"418","types":["water"],"bases":330,"color":"brown","name":"Buizel"},{"id":"419","types":["water"],"bases":495,"color":"brown","name":"Floatzel"},{"id":"420","types":["grass"],"bases":275,"color":"pink","name":"Cherubi"},{"id":"421","types":["grass"],"bases":450,"color":"purple","name":"Cherrim"},{"id":"422","types":["water"],"bases":325,"color":"purple","name":"Shellos"},{"id":"423","types":["water","ground"],"bases":475,"color":"purple","name":"Gastrodon"},{"id":"424","types":["normal"],"bases":482,"color":"purple","name":"Ambipom"},{"id":"425","types":["ghost","flying"],"bases":348,"color":"purple","name":"Drifloon"},{"id":"426","types":["ghost","flying"],"bases":498,"color":"purple","name":"Drifblim"},{"id":"427","types":["normal"],"bases":350,"color":"brown","name":"Buneary"},{"id":"428","types":["normal"],"bases":480,"color":"brown","name":"Lopunny"},{"id":"429","types":["ghost"],"bases":495,"color":"purple","name":"Mismagius"},{"id":"430","types":["dark","flying"],"bases":505,"color":"black","name":"Honchkrow"},{"id":"431","types":["normal"],"bases":310,"color":"gray","name":"Glameow"},{"id":"432","types":["normal"],"bases":452,"color":"gray","name":"Purugly"},{"id":"433","types":["psychic"],"bases":285,"color":"yellow","name":"Chingling"},{"id":"434","types":["poison","dark"],"bases":329,"color":"purple","name":"Stunky"},{"id":"435","types":["poison","dark"],"bases":479,"color":"purple","name":"Skuntank"},{"id":"436","types":["steel","psychic"],"bases":300,"color":"green","name":"Bronzor"},{"id":"437","types":["steel","psychic"],"bases":500,"color":"green","name":"Bronzong"},{"id":"438","types":["rock"],"bases":290,"color":"brown","name":"Bonsly"},{"id":"439","types":["psychic","fairy"],"bases":310,"color":"pink","name":"Mime Jr."},{"id":"440","types":["normal"],"bases":220,"color":"pink","name":"Happiny"},{"id":"441","types":["normal","flying"],"bases":411,"color":"black","name":"Chatot"},{"id":"442","types":["ghost","dark"],"bases":485,"color":"purple","name":"Spiritomb"},{"id":"443","types":["dragon","ground"],"bases":300,"color":"blue","name":"Gible"},{"id":"444","types":["dragon","ground"],"bases":410,"color":"blue","name":"Gabite"},{"id":"445","types":["dragon","ground"],"bases":600,"color":"blue","name":"Garchomp"},{"id":"446","types":["normal"],"bases":390,"color":"black","name":"Munchlax"},{"id":"447","types":["fighting"],"bases":285,"color":"blue","name":"Riolu"},{"id":"448","types":["fighting","steel"],"bases":525,"color":"blue","name":"Lucario"},{"id":"449","types":["ground"],"bases":330,"color":"brown","name":"Hippopotas"},{"id":"450","types":["ground"],"bases":525,"color":"brown","name":"Hippowdon"},{"id":"451","types":["poison","bug"],"bases":330,"color":"purple","name":"Skorupi"},{"id":"452","types":["poison","dark"],"bases":500,"color":"purple","name":"Drapion"},{"id":"453","types":["poison","fighting"],"bases":300,"color":"blue","name":"Croagunk"},{"id":"454","types":["poison","fighting"],"bases":490,"color":"blue","name":"Toxicroak"},{"id":"455","types":["grass"],"bases":454,"color":"green","name":"Carnivine"},{"id":"456","types":["water"],"bases":330,"color":"blue","name":"Finneon"},{"id":"457","types":["water"],"bases":460,"color":"blue","name":"Lumineon"},{"id":"458","types":["water","flying"],"bases":345,"color":"blue","name":"Mantyke"},{"id":"459","types":["grass","ice"],"bases":334,"color":"white","name":"Snover"},{"id":"460","types":["grass","ice"],"bases":494,"color":"white","name":"Abomasnow"},{"id":"461","types":["dark","ice"],"bases":510,"color":"black","name":"Weavile"},{"id":"462","types":["electric","steel"],"bases":535,"color":"gray","name":"Magnezone"},{"id":"463","types":["normal"],"bases":515,"color":"pink","name":"Lickilicky"},{"id":"464","types":["ground","rock"],"bases":535,"color":"gray","name":"Rhyperior"},{"id":"465","types":["grass"],"bases":535,"color":"blue","name":"Tangrowth"},{"id":"466","types":["electric"],"bases":540,"color":"yellow","name":"Electivire"},{"id":"467","types":["fire"],"bases":540,"color":"red","name":"Magmortar"},{"id":"468","types":["fairy","flying"],"bases":545,"color":"white","name":"Togekiss"},{"id":"469","types":["bug","flying"],"bases":515,"color":"green","name":"Yanmega"},{"id":"470","types":["grass"],"bases":525,"color":"green","name":"Leafeon"},{"id":"471","types":["ice"],"bases":525,"color":"blue","name":"Glaceon"},{"id":"472","types":["ground","flying"],"bases":510,"color":"purple","name":"Gliscor"},{"id":"473","types":["ice","ground"],"bases":530,"color":"brown","name":"Mamoswine"},{"id":"474","types":["normal"],"bases":535,"color":"red","name":"Porygon-Z"},{"id":"475","types":["psychic","fighting"],"bases":518,"color":"white","name":"Gallade"},{"id":"476","types":["rock","steel"],"bases":525,"color":"gray","name":"Probopass"},{"id":"477","types":["ghost"],"bases":525,"color":"black","name":"Dusknoir"},{"id":"478","types":["ice","ghost"],"bases":480,"color":"white","name":"Froslass"},{"id":"479","types":["electric","ghost"],"bases":440,"color":"red","name":"Rotom"},{"id":"480","types":["psychic"],"bases":580,"color":"yellow","name":"Uxie"},{"id":"481","types":["psychic"],"bases":580,"color":"pink","name":"Mesprit"},{"id":"482","types":["psychic"],"bases":580,"color":"blue","name":"Azelf"},{"id":"483","types":["steel","dragon"],"bases":680,"color":"white","name":"Dialga"},{"id":"484","types":["water","dragon"],"bases":680,"color":"purple","name":"Palkia"},{"id":"485","types":["fire","steel"],"bases":600,"color":"brown","name":"Heatran"},{"id":"486","types":["normal"],"bases":670,"color":"white","name":"Regigigas"},{"id":"487","types":["ghost","dragon"],"bases":680,"color":"black","name":"Altered Giratina"},{"id":"488","types":["psychic"],"bases":600,"color":"yellow","name":"Cresselia"},{"id":"489","types":["water"],"bases":480,"color":"blue","name":"Phione"},{"id":"490","types":["water"],"bases":600,"color":"blue","name":"Manaphy"},{"id":"491","types":["dark"],"bases":600,"color":"black","name":"Darkrai"},{"id":"492","types":["grass"],"bases":600,"color":"green","name":"Land Shaymin"},{"id":"493","types":["normal"],"bases":720,"color":"white","name":"Arceus"},{"id":"494","types":["psychic","fire"],"bases":600,"color":"yellow","name":"Victini"},{"id":"495","types":["grass"],"bases":308,"color":"green","name":"Snivy"},{"id":"496","types":["grass"],"bases":413,"color":"green","name":"Servine"},{"id":"497","types":["grass"],"bases":528,"color":"green","name":"Serperior"},{"id":"498","types":["fire"],"bases":308,"color":"red","name":"Tepig"},{"id":"499","types":["fire","fighting"],"bases":418,"color":"red","name":"Pignite"},{"id":"500","types":["fire","fighting"],"bases":528,"color":"red","name":"Emboar"},{"id":"501","types":["water"],"bases":308,"color":"blue","name":"Oshawott"},{"id":"502","types":["water"],"bases":413,"color":"blue","name":"Dewott"},{"id":"503","types":["water"],"bases":528,"color":"blue","name":"Samurott"},{"id":"504","types":["normal"],"bases":255,"color":"brown","name":"Patrat"},{"id":"505","types":["normal"],"bases":420,"color":"brown","name":"Watchog"},{"id":"506","types":["normal"],"bases":275,"color":"brown","name":"Lillipup"},{"id":"507","types":["normal"],"bases":370,"color":"gray","name":"Herdier"},{"id":"508","types":["normal"],"bases":500,"color":"gray","name":"Stoutland"},{"id":"509","types":["dark"],"bases":281,"color":"purple","name":"Purrloin"},{"id":"510","types":["dark"],"bases":446,"color":"purple","name":"Liepard"},{"id":"511","types":["grass"],"bases":316,"color":"green","name":"Pansage"},{"id":"512","types":["grass"],"bases":498,"color":"green","name":"Simisage"},{"id":"513","types":["fire"],"bases":316,"color":"red","name":"Pansear"},{"id":"514","types":["fire"],"bases":498,"color":"red","name":"Simisear"},{"id":"515","types":["water"],"bases":316,"color":"blue","name":"Panpour"},{"id":"516","types":["water"],"bases":498,"color":"blue","name":"Simipour"},{"id":"517","types":["psychic"],"bases":292,"color":"pink","name":"Munna"},{"id":"518","types":["psychic"],"bases":487,"color":"pink","name":"Musharna"},{"id":"519","types":["normal","flying"],"bases":264,"color":"gray","name":"Pidove"},{"id":"520","types":["normal","flying"],"bases":358,"color":"gray","name":"Tranquill"},{"id":"521","types":["normal","flying"],"bases":488,"color":"gray","name":"Unfezant"},{"id":"522","types":["electric"],"bases":295,"color":"black","name":"Blitzle"},{"id":"523","types":["electric"],"bases":497,"color":"black","name":"Zebstrika"},{"id":"524","types":["rock"],"bases":280,"color":"blue","name":"Roggenrola"},{"id":"525","types":["rock"],"bases":390,"color":"blue","name":"Boldore"},{"id":"526","types":["rock"],"bases":515,"color":"blue","name":"Gigalith"},{"id":"527","types":["psychic","flying"],"bases":323,"color":"blue","name":"Woobat"},{"id":"528","types":["psychic","flying"],"bases":425,"color":"blue","name":"Swoobat"},{"id":"529","types":["ground"],"bases":328,"color":"gray","name":"Drilbur"},{"id":"530","types":["ground","steel"],"bases":508,"color":"gray","name":"Excadrill"},{"id":"531","types":["normal"],"bases":445,"color":"pink","name":"Audino"},{"id":"532","types":["fighting"],"bases":305,"color":"gray","name":"Timburr"},{"id":"533","types":["fighting"],"bases":405,"color":"gray","name":"Gurdurr"},{"id":"534","types":["fighting"],"bases":505,"color":"brown","name":"Conkeldurr"},{"id":"535","types":["water"],"bases":294,"color":"blue","name":"Tympole"},{"id":"536","types":["water","ground"],"bases":384,"color":"blue","name":"Palpitoad"},{"id":"537","types":["water","ground"],"bases":509,"color":"blue","name":"Seismitoad"},{"id":"538","types":["fighting"],"bases":465,"color":"red","name":"Throh"},{"id":"539","types":["fighting"],"bases":465,"color":"blue","name":"Sawk"},{"id":"540","types":["bug","grass"],"bases":310,"color":"yellow","name":"Sewaddle"},{"id":"541","types":["bug","grass"],"bases":380,"color":"green","name":"Swadloon"},{"id":"542","types":["bug","grass"],"bases":500,"color":"yellow","name":"Leavanny"},{"id":"543","types":["bug","poison"],"bases":260,"color":"red","name":"Venipede"},{"id":"544","types":["bug","poison"],"bases":360,"color":"gray","name":"Whirlipede"},{"id":"545","types":["bug","poison"],"bases":485,"color":"red","name":"Scolipede"},{"id":"546","types":["grass","fairy"],"bases":280,"color":"green","name":"Cottonee"},{"id":"547","types":["grass","fairy"],"bases":480,"color":"green","name":"Whimsicott"},{"id":"548","types":["grass"],"bases":280,"color":"green","name":"Petilil"},{"id":"549","types":["grass"],"bases":480,"color":"green","name":"Lilligant"},{"id":"550","types":["water"],"bases":460,"color":"green","name":"Basculin"},{"id":"551","types":["ground","dark"],"bases":292,"color":"brown","name":"Sandile"},{"id":"552","types":["ground","dark"],"bases":351,"color":"brown","name":"Krokorok"},{"id":"553","types":["ground","dark"],"bases":519,"color":"red","name":"Krookodile"},{"id":"554","types":["fire"],"bases":315,"color":"red","name":"Darumaka"},{"id":"555","types":["fire"],"bases":480,"color":"red","name":"Standard Darmanitan"},{"id":"556","types":["grass"],"bases":461,"color":"green","name":"Maractus"},{"id":"557","types":["bug","rock"],"bases":325,"color":"red","name":"Dwebble"},{"id":"558","types":["bug","rock"],"bases":485,"color":"red","name":"Crustle"},{"id":"559","types":["dark","fighting"],"bases":348,"color":"yellow","name":"Scraggy"},{"id":"560","types":["dark","fighting"],"bases":488,"color":"red","name":"Scrafty"},{"id":"561","types":["psychic","flying"],"bases":490,"color":"black","name":"Sigilyph"},{"id":"562","types":["ghost"],"bases":303,"color":"black","name":"Yamask"},{"id":"563","types":["ghost"],"bases":483,"color":"yellow","name":"Cofagrigus"},{"id":"564","types":["water","rock"],"bases":355,"color":"blue","name":"Tirtouga"},{"id":"565","types":["water","rock"],"bases":495,"color":"blue","name":"Carracosta"},{"id":"566","types":["rock","flying"],"bases":401,"color":"yellow","name":"Archen"},{"id":"567","types":["rock","flying"],"bases":567,"color":"yellow","name":"Archeops"},{"id":"568","types":["poison"],"bases":329,"color":"green","name":"Trubbish"},{"id":"569","types":["poison"],"bases":474,"color":"green","name":"Garbodor"},{"id":"570","types":["dark"],"bases":330,"color":"gray","name":"Zorua"},{"id":"571","types":["dark"],"bases":510,"color":"gray","name":"Zoroark"},{"id":"572","types":["normal"],"bases":300,"color":"gray","name":"Minccino"},{"id":"573","types":["normal"],"bases":470,"color":"gray","name":"Cinccino"},{"id":"574","types":["psychic"],"bases":290,"color":"purple","name":"Gothita"},{"id":"575","types":["psychic"],"bases":390,"color":"purple","name":"Gothorita"},{"id":"576","types":["psychic"],"bases":490,"color":"purple","name":"Gothitelle"},{"id":"577","types":["psychic"],"bases":290,"color":"green","name":"Solosis"},{"id":"578","types":["psychic"],"bases":370,"color":"green","name":"Duosion"},{"id":"579","types":["psychic"],"bases":490,"color":"green","name":"Reuniclus"},{"id":"580","types":["water","flying"],"bases":305,"color":"blue","name":"Ducklett"},{"id":"581","types":["water","flying"],"bases":473,"color":"white","name":"Swanna"},{"id":"582","types":["ice"],"bases":305,"color":"white","name":"Vanillite"},{"id":"583","types":["ice"],"bases":395,"color":"white","name":"Vanillish"},{"id":"584","types":["ice"],"bases":535,"color":"white","name":"Vanilluxe"},{"id":"585","types":["normal","grass"],"bases":335,"color":"pink","name":"Deerling"},{"id":"586","types":["normal","grass"],"bases":475,"color":"brown","name":"Sawsbuck"},{"id":"587","types":["electric","flying"],"bases":428,"color":"white","name":"Emolga"},{"id":"588","types":["bug"],"bases":315,"color":"blue","name":"Karrablast"},{"id":"589","types":["bug","steel"],"bases":495,"color":"gray","name":"Escavalier"},{"id":"590","types":["grass","poison"],"bases":294,"color":"white","name":"Foongus"},{"id":"591","types":["grass","poison"],"bases":464,"color":"white","name":"Amoonguss"},{"id":"592","types":["water","ghost"],"bases":335,"color":"white","name":"Frillish"},{"id":"593","types":["water","ghost"],"bases":480,"color":"white","name":"Jellicent"},{"id":"594","types":["water"],"bases":470,"color":"pink","name":"Alomomola"},{"id":"595","types":["bug","electric"],"bases":319,"color":"yellow","name":"Joltik"},{"id":"596","types":["bug","electric"],"bases":472,"color":"yellow","name":"Galvantula"},{"id":"597","types":["grass","steel"],"bases":305,"color":"gray","name":"Ferroseed"},{"id":"598","types":["grass","steel"],"bases":489,"color":"gray","name":"Ferrothorn"},{"id":"599","types":["steel"],"bases":300,"color":"gray","name":"Klink"},{"id":"600","types":["steel"],"bases":440,"color":"gray","name":"Klang"},{"id":"601","types":["steel"],"bases":520,"color":"gray","name":"Klinklang"},{"id":"602","types":["electric"],"bases":275,"color":"white","name":"Tynamo"},{"id":"603","types":["electric"],"bases":405,"color":"blue","name":"Eelektrik"},{"id":"604","types":["electric"],"bases":515,"color":"blue","name":"Eelektross"},{"id":"605","types":["psychic"],"bases":335,"color":"blue","name":"Elgyem"},{"id":"606","types":["psychic"],"bases":485,"color":"brown","name":"Beheeyem"},{"id":"607","types":["ghost","fire"],"bases":275,"color":"white","name":"Litwick"},{"id":"608","types":["ghost","fire"],"bases":370,"color":"black","name":"Lampent"},{"id":"609","types":["ghost","fire"],"bases":520,"color":"black","name":"Chandelure"},{"id":"610","types":["dragon"],"bases":320,"color":"green","name":"Axew"},{"id":"611","types":["dragon"],"bases":410,"color":"green","name":"Fraxure"},{"id":"612","types":["dragon"],"bases":540,"color":"yellow","name":"Haxorus"},{"id":"613","types":["ice"],"bases":305,"color":"white","name":"Cubchoo"},{"id":"614","types":["ice"],"bases":505,"color":"white","name":"Beartic"},{"id":"615","types":["ice"],"bases":515,"color":"blue","name":"Cryogonal"},{"id":"616","types":["bug"],"bases":305,"color":"red","name":"Shelmet"},{"id":"617","types":["bug"],"bases":495,"color":"red","name":"Accelgor"},{"id":"618","types":["ground","electric"],"bases":471,"color":"brown","name":"Stunfisk"},{"id":"619","types":["fighting"],"bases":350,"color":"yellow","name":"Mienfoo"},{"id":"620","types":["fighting"],"bases":510,"color":"purple","name":"Mienshao"},{"id":"621","types":["dragon"],"bases":485,"color":"red","name":"Druddigon"},{"id":"622","types":["ground","ghost"],"bases":303,"color":"green","name":"Golett"},{"id":"623","types":["ground","ghost"],"bases":483,"color":"green","name":"Golurk"},{"id":"624","types":["dark","steel"],"bases":340,"color":"red","name":"Pawniard"},{"id":"625","types":["dark","steel"],"bases":490,"color":"red","name":"Bisharp"},{"id":"626","types":["normal"],"bases":490,"color":"brown","name":"Bouffalant"},{"id":"627","types":["normal","flying"],"bases":350,"color":"white","name":"Rufflet"},{"id":"628","types":["normal","flying"],"bases":510,"color":"red","name":"Braviary"},{"id":"629","types":["dark","flying"],"bases":370,"color":"brown","name":"Vullaby"},{"id":"630","types":["dark","flying"],"bases":510,"color":"brown","name":"Mandibuzz"},{"id":"631","types":["fire"],"bases":484,"color":"red","name":"Heatmor"},{"id":"632","types":["bug","steel"],"bases":484,"color":"gray","name":"Durant"},{"id":"633","types":["dark","dragon"],"bases":300,"color":"blue","name":"Deino"},{"id":"634","types":["dark","dragon"],"bases":420,"color":"blue","name":"Zweilous"},{"id":"635","types":["dark","dragon"],"bases":600,"color":"blue","name":"Hydreigon"},{"id":"636","types":["bug","fire"],"bases":360,"color":"white","name":"Larvesta"},{"id":"637","types":["bug","fire"],"bases":550,"color":"white","name":"Volcarona"},{"id":"638","types":["steel","fighting"],"bases":580,"color":"blue","name":"Cobalion"},{"id":"639","types":["rock","fighting"],"bases":580,"color":"gray","name":"Terrakion"},{"id":"640","types":["grass","fighting"],"bases":580,"color":"green","name":"Virizion"},{"id":"641","types":["flying"],"bases":580,"color":"green","name":"Incarnate Tornadus"},{"id":"642","types":["electric","flying"],"bases":580,"color":"blue","name":"Incarnate Thundurus"},{"id":"643","types":["dragon","fire"],"bases":680,"color":"white","name":"Reshiram"},{"id":"644","types":["dragon","electric"],"bases":680,"color":"black","name":"Zekrom"},{"id":"645","types":["ground","flying"],"bases":600,"color":"brown","name":"Incarnate Landorus"},{"id":"646","types":["dragon","ice"],"bases":660,"color":"gray","name":"Kyurem"},{"id":"647","types":["water","fighting"],"bases":580,"color":"yellow","name":"Ordinary Keldeo"},{"id":"648","types":["normal","psychic"],"bases":600,"color":"white","name":"Aria Meloetta"},{"id":"649","types":["bug","steel"],"bases":600,"color":"purple","name":"Genesect"},{"id":"650","types":["grass"],"bases":313,"color":"green","name":"Chespin"},{"id":"651","types":["grass"],"bases":405,"color":"green","name":"Quilladin"},{"id":"652","types":["grass","fighting"],"bases":530,"color":"green","name":"Chesnaught"},{"id":"653","types":["fire"],"bases":307,"color":"red","name":"Fennekin"},{"id":"654","types":["fire"],"bases":409,"color":"red","name":"Braixen"},{"id":"655","types":["fire","psychic"],"bases":534,"color":"red","name":"Delphox"},{"id":"656","types":["water"],"bases":314,"color":"blue","name":"Froakie"},{"id":"657","types":["water"],"bases":405,"color":"blue","name":"Frogadier"},{"id":"658","types":["water","dark"],"bases":530,"color":"blue","name":"Greninja"},{"id":"659","types":["normal"],"bases":237,"color":"brown","name":"Bunnelby"},{"id":"660","types":["normal","ground"],"bases":423,"color":"brown","name":"Diggersby"},{"id":"661","types":["normal","flying"],"bases":278,"color":"red","name":"Fletchling"},{"id":"662","types":["fire","flying"],"bases":382,"color":"red","name":"Fletchinder"},{"id":"663","types":["fire","flying"],"bases":499,"color":"red","name":"Talonflame"},{"id":"664","types":["bug"],"bases":200,"color":"black","name":"Scatterbug"},{"id":"665","types":["bug"],"bases":213,"color":"black","name":"Spewpa"},{"id":"666","types":["bug","flying"],"bases":411,"color":"white","name":"Vivillon"},{"id":"667","types":["fire","normal"],"bases":369,"color":"brown","name":"Litleo"},{"id":"668","types":["fire","normal"],"bases":507,"color":"brown","name":"Pyroar"},{"id":"669","types":["fairy"],"bases":303,"color":"white","name":"Flabébé"},{"id":"670","types":["fairy"],"bases":371,"color":"white","name":"Floette"},{"id":"671","types":["fairy"],"bases":552,"color":"white","name":"Florges"},{"id":"672","types":["grass"],"bases":350,"color":"brown","name":"Skiddo"},{"id":"673","types":["grass"],"bases":531,"color":"brown","name":"Gogoat"},{"id":"674","types":["fighting"],"bases":348,"color":"white","name":"Pancham"},{"id":"675","types":["fighting","dark"],"bases":495,"color":"white","name":"Pangoro"},{"id":"676","types":["normal"],"bases":472,"color":"white","name":"Furfrou"},{"id":"677","types":["psychic"],"bases":355,"color":"gray","name":"Espurr"},{"id":"678","types":["psychic"],"bases":466,"color":"blue","name":"Meowstic"},{"id":"679","types":["steel","ghost"],"bases":325,"color":"brown","name":"Honedge"},{"id":"680","types":["steel","ghost"],"bases":448,"color":"brown","name":"Doublade"},{"id":"681","types":["steel","ghost"],"bases":520,"color":"brown","name":"Aegislash"},{"id":"682","types":["fairy"],"bases":341,"color":"pink","name":"Spritzee"},{"id":"683","types":["fairy"],"bases":462,"color":"pink","name":"Aromatisse"},{"id":"684","types":["fairy"],"bases":341,"color":"white","name":"Swirlix"},{"id":"685","types":["fairy"],"bases":480,"color":"white","name":"Slurpuff"},{"id":"686","types":["dark","psychic"],"bases":288,"color":"blue","name":"Inkay"},{"id":"687","types":["dark","psychic"],"bases":482,"color":"blue","name":"Malamar"},{"id":"688","types":["rock","water"],"bases":306,"color":"brown","name":"Binacle"},{"id":"689","types":["rock","water"],"bases":500,"color":"brown","name":"Barbaracle"},{"id":"690","types":["poison","water"],"bases":320,"color":"brown","name":"Skrelp"},{"id":"691","types":["poison","dragon"],"bases":494,"color":"brown","name":"Dragalge"},{"id":"692","types":["water"],"bases":330,"color":"blue","name":"Clauncher"},{"id":"693","types":["water"],"bases":500,"color":"blue","name":"Clawitzer"},{"id":"694","types":["electric","normal"],"bases":289,"color":"yellow","name":"Helioptile"},{"id":"695","types":["electric","normal"],"bases":481,"color":"yellow","name":"Heliolisk"},{"id":"696","types":["rock","dragon"],"bases":362,"color":"brown","name":"Tyrunt"},{"id":"697","types":["rock","dragon"],"bases":521,"color":"red","name":"Tyrantrum"},{"id":"698","types":["rock","ice"],"bases":362,"color":"blue","name":"Amaura"},{"id":"699","types":["rock","ice"],"bases":521,"color":"blue","name":"Aurorus"},{"id":"700","types":["fairy"],"bases":525,"color":"pink","name":"Sylveon"},{"id":"701","types":["fighting","flying"],"bases":500,"color":"green","name":"Hawlucha"},{"id":"702","types":["electric","fairy"],"bases":431,"color":"yellow","name":"Dedenne"},{"id":"703","types":["rock","fairy"],"bases":500,"color":"gray","name":"Carbink"},{"id":"704","types":["dragon"],"bases":300,"color":"purple","name":"Goomy"},{"id":"705","types":["dragon"],"bases":452,"color":"purple","name":"Sliggoo"},{"id":"706","types":["dragon"],"bases":600,"color":"purple","name":"Goodra"},{"id":"707","types":["steel","fairy"],"bases":470,"color":"gray","name":"Klefki"},{"id":"708","types":["ghost","grass"],"bases":309,"color":"brown","name":"Phantump"},{"id":"709","types":["ghost","grass"],"bases":474,"color":"brown","name":"Trevenant"},{"id":"710","types":["ghost","grass"],"bases":335,"color":"brown","name":"Average Pumpkaboo"},{"id":"711","types":["ghost","grass"],"bases":494,"color":"brown","name":"Average Gourgeist"},{"id":"712","types":["ice"],"bases":304,"color":"blue","name":"Bergmite"},{"id":"713","types":["ice"],"bases":514,"color":"blue","name":"Avalugg"},{"id":"714","types":["flying","dragon"],"bases":245,"color":"purple","name":"Noibat"},{"id":"715","types":["flying","dragon"],"bases":535,"color":"purple","name":"Noivern"},{"id":"716","types":["fairy"],"bases":680,"color":"blue","name":"Xerneas"},{"id":"717","types":["dark","flying"],"bases":680,"color":"red","name":"Yveltal"},{"id":"718","types":["dragon","ground"],"bases":600,"color":"green","name":"Zygarde"},{"id":"719","types":["rock","fairy"],"bases":600,"color":"pink","name":"Diancie"},{"id":"720","types":["psychic","ghost"],"bases":600,"color":"purple","name":"Confined Hoopa"},{"id":"721","types":["fire","water"],"bases":600,"color":"brown","name":"Volcanion"},{"id":"722","types":["grass","flying"],"bases":320,"color":"brown","name":"Rowlet"},{"id":"723","types":["grass","flying"],"bases":420,"color":"brown","name":"Dartrix"},{"id":"724","types":["grass","ghost"],"bases":530,"color":"brown","name":"Decidueye"},{"id":"725","types":["fire"],"bases":320,"color":"red","name":"Litten"},{"id":"726","types":["fire"],"bases":420,"color":"red","name":"Torracat"},{"id":"727","types":["fire","dark"],"bases":530,"color":"red","name":"Incineroar"},{"id":"728","types":["water"],"bases":320,"color":"blue","name":"Popplio"},{"id":"729","types":["water"],"bases":420,"color":"blue","name":"Brionne"},{"id":"730","types":["water","fairy"],"bases":530,"color":"blue","name":"Primarina"},{"id":"731","types":["normal","flying"],"bases":265,"color":"black","name":"Pikipek"},{"id":"732","types":["normal","flying"],"bases":355,"color":"black","name":"Trumbeak"},{"id":"733","types":["normal","flying"],"bases":485,"color":"black","name":"Toucannon"},{"id":"734","types":["normal"],"bases":253,"color":"brown","name":"Yungoos"},{"id":"735","types":["normal"],"bases":418,"color":"brown","name":"Gumshoos"},{"id":"736","types":["bug"],"bases":300,"color":"gray","name":"Grubbin"},{"id":"737","types":["bug","electric"],"bases":400,"color":"green","name":"Charjabug"},{"id":"738","types":["bug","electric"],"bases":500,"color":"blue","name":"Vikavolt"},{"id":"739","types":["fighting"],"bases":338,"color":"purple","name":"Crabrawler"},{"id":"740","types":["fighting","ice"],"bases":478,"color":"white","name":"Crabominable"},{"id":"741","types":["fire","flying"],"bases":476,"color":"red","name":"Baile Oricorio"},{"id":"742","types":["bug","fairy"],"bases":304,"color":"yellow","name":"Cutiefly"},{"id":"743","types":["bug","fairy"],"bases":464,"color":"yellow","name":"Ribombee"},{"id":"744","types":["rock"],"bases":280,"color":"brown","name":"Rockruff"},{"id":"745","types":["rock"],"bases":487,"color":"brown","name":"Lycanroc"},{"id":"746","types":["water"],"bases":175,"color":"blue","name":"Wishiwashi"},{"id":"747","types":["poison","water"],"bases":305,"color":"blue","name":"Mareanie"},{"id":"748","types":["poison","water"],"bases":495,"color":"blue","name":"Toxapex"},{"id":"749","types":["ground"],"bases":385,"color":"brown","name":"Mudbray"},{"id":"750","types":["ground"],"bases":500,"color":"brown","name":"Mudsdale"},{"id":"751","types":["water","bug"],"bases":269,"color":"green","name":"Dewpider"},{"id":"752","types":["water","bug"],"bases":454,"color":"green","name":"Araquanid"},{"id":"753","types":["grass"],"bases":250,"color":"pink","name":"Fomantis"},{"id":"754","types":["grass"],"bases":480,"color":"pink","name":"Lurantis"},{"id":"755","types":["grass","fairy"],"bases":285,"color":"purple","name":"Morelull"},{"id":"756","types":["grass","fairy"],"bases":405,"color":"purple","name":"Shiinotic"},{"id":"757","types":["poison","fire"],"bases":320,"color":"black","name":"Salandit"},{"id":"758","types":["poison","fire"],"bases":480,"color":"black","name":"Salazzle"},{"id":"759","types":["normal","fighting"],"bases":340,"color":"pink","name":"Stufful"},{"id":"760","types":["normal","fighting"],"bases":500,"color":"pink","name":"Bewear"},{"id":"761","types":["grass"],"bases":210,"color":"purple","name":"Bounsweet"},{"id":"762","types":["grass"],"bases":290,"color":"purple","name":"Steenee"},{"id":"763","types":["grass"],"bases":510,"color":"purple","name":"Tsareena"},{"id":"764","types":["fairy"],"bases":485,"color":"green","name":"Comfey"},{"id":"765","types":["normal","psychic"],"bases":490,"color":"white","name":"Oranguru"},{"id":"766","types":["fighting"],"bases":490,"color":"white","name":"Passimian"},{"id":"767","types":["bug","water"],"bases":230,"color":"gray","name":"Wimpod"},{"id":"768","types":["bug","water"],"bases":530,"color":"gray","name":"Golisopod"},{"id":"769","types":["ghost","ground"],"bases":320,"color":"brown","name":"Sandygast"},{"id":"770","types":["ghost","ground"],"bases":480,"color":"brown","name":"Palossand"},{"id":"771","types":["water"],"bases":410,"color":"black","name":"Pyukumuku"},{"id":"772","types":["normal"],"bases":534,"color":"gray","name":"Type: Null"},{"id":"773","types":["normal"],"bases":570,"color":"gray","name":"Silvally"},{"id":"774","types":["rock","flying"],"bases":440,"color":"brown","name":"Minior"},{"id":"775","types":["normal"],"bases":480,"color":"blue","name":"Komala"},{"id":"776","types":["fire","dragon"],"bases":485,"color":"red","name":"Turtonator"},{"id":"777","types":["electric","steel"],"bases":435,"color":"gray","name":"Togedemaru"},{"id":"778","types":["ghost","fairy"],"bases":476,"color":"yellow","name":"Mimikyu"},{"id":"779","types":["water","psychic"],"bases":475,"color":"pink","name":"Bruxish"},{"id":"780","types":["normal","dragon"],"bases":485,"color":"white","name":"Drampa"},{"id":"781","types":["ghost","grass"],"bases":517,"color":"green","name":"Dhelmise"},{"id":"782","types":["dragon"],"bases":300,"color":"gray","name":"Jangmo-o"},{"id":"783","types":["dragon","fighting"],"bases":420,"color":"gray","name":"Hakamo-o"},{"id":"784","types":["dragon","fighting"],"bases":600,"color":"gray","name":"Kommo-o"},{"id":"785","types":["electric","fairy"],"bases":570,"color":"yellow","name":"Tapu Koko"},{"id":"786","types":["psychic","fairy"],"bases":570,"color":"pink","name":"Tapu Lele"},{"id":"787","types":["grass","fairy"],"bases":570,"color":"red","name":"Tapu Bulu"},{"id":"788","types":["water","fairy"],"bases":570,"color":"purple","name":"Tapu Fini"},{"id":"789","types":["psychic"],"bases":200,"color":"blue","name":"Cosmog"},{"id":"790","types":["psychic"],"bases":400,"color":"blue","name":"Cosmoem"},{"id":"791","types":["psychic","steel"],"bases":680,"color":"white","name":"Solgaleo"},{"id":"792","types":["psychic","ghost"],"bases":680,"color":"purple","name":"Lunala"},{"id":"793","types":["rock","poison"],"bases":570,"color":"white","name":"Nihilego"},{"id":"794","types":["bug","fighting"],"bases":570,"color":"red","name":"Buzzwole"},{"id":"795","types":["bug","fighting"],"bases":570,"color":"white","name":"Pheromosa"},{"id":"796","types":["electric"],"bases":570,"color":"black","name":"Xurkitree"},{"id":"797","types":["steel","flying"],"bases":570,"color":"green","name":"Celesteela"},{"id":"798","types":["grass","steel"],"bases":570,"color":"white","name":"Kartana"},{"id":"799","types":["dark","dragon"],"bases":570,"color":"black","name":"Guzzlord"},{"id":"800","types":["psychic"],"bases":600,"color":"black","name":"Necrozma"},{"id":"801","types":["steel","fairy"],"bases":600,"color":"gray","name":"Magearna"},{"id":"802","types":["fighting","ghost"],"bases":600,"color":"gray","name":"Marshadow"},{"id":"803","types":["poison"],"bases":420,"color":"purple","name":"Poipole"},{"id":"804","types":["poison","dragon"],"bases":540,"color":"purple","name":"Naganadel"},{"id":"805","types":["rock","steel"],"bases":570,"color":"gray","name":"Stakataka"},{"id":"806","types":["fire","ghost"],"bases":570,"color":"white","name":"Blacephalon"},{"id":"807","types":["electric"],"bases":600,"color":"yellow","name":"Zeraora"}]